nnapprox/__init__.py
nnapprox/_version.py
nnapprox/backends/torch/__init__.py
nnapprox/backends/torch/approximator.py
nnapprox/backends/torch/models.py
nnapprox/core/__init__.py
nnapprox/core/base.py
nnapprox/core/exceptions.py
nnapprox/core/utils.py
nnapprox-0.3.2.dist-info/METADATA
nnapprox-0.3.2.dist-info/WHEEL
nnapprox-0.3.2.dist-info/licenses/LICENSE
nnapprox-0.3.2.dist-info/RECORD
