Metadata-Version: 2.4
Name: nnapprox
Version: 0.3.2
Summary: Neural network approximation for high-dimensional functional relations
Project-URL: Homepage, https://github.com/zierenberg/nnapprox
Project-URL: Issues, https://github.com/zierenberg/nnapprox/issues
Project-URL: Documentation, https://nnapprox.readthedocs.io
Author-email: Johannes Zierenberg <johannes.zierenberg@gmail.com>
License: MIT License
License-File: LICENSE
Requires-Python: >=3.8
Requires-Dist: numpy
Requires-Dist: pandas
Requires-Dist: scikit-learn
Requires-Dist: scipy
Requires-Dist: tqdm
Provides-Extra: all
Requires-Dist: cloudpickle; extra == 'all'
Requires-Dist: torch>=1.9; extra == 'all'
Provides-Extra: dev
Requires-Dist: flake8; extra == 'dev'
Requires-Dist: pytest; extra == 'dev'
Requires-Dist: pytest-cov; extra == 'dev'
Provides-Extra: torch
Requires-Dist: torch>=1.9; extra == 'torch'
